LICENSE
MANIFEST.in
README.md
setup.cfg
setup.py
src/onelogin/__init__.py
src/onelogin/saml2/__init__.py
src/onelogin/saml2/auth.py
src/onelogin/saml2/authn_request.py
src/onelogin/saml2/constants.py
src/onelogin/saml2/errors.py
src/onelogin/saml2/idp_metadata_parser.py
src/onelogin/saml2/logout_request.py
src/onelogin/saml2/logout_response.py
src/onelogin/saml2/metadata.py
src/onelogin/saml2/response.py
src/onelogin/saml2/settings.py
src/onelogin/saml2/utils.py
src/onelogin/saml2/schemas/saml-schema-assertion-2.0.xsd
src/onelogin/saml2/schemas/saml-schema-authn-context-2.0.xsd
src/onelogin/saml2/schemas/saml-schema-authn-context-types-2.0.xsd
src/onelogin/saml2/schemas/saml-schema-metadata-2.0.xsd
src/onelogin/saml2/schemas/saml-schema-protocol-2.0.xsd
src/onelogin/saml2/schemas/sstc-metadata-attr.xsd
src/onelogin/saml2/schemas/sstc-saml-attribute-ext.xsd
src/onelogin/saml2/schemas/sstc-saml-metadata-algsupport-v1.0.xsd
src/onelogin/saml2/schemas/sstc-saml-metadata-ui-v1.0.xsd
src/onelogin/saml2/schemas/xenc-schema.xsd
src/onelogin/saml2/schemas/xml.xsd
src/onelogin/saml2/schemas/xmldsig-core-schema.xsd
src/python_saml_nocert.egg-info/PKG-INFO
src/python_saml_nocert.egg-info/SOURCES.txt
src/python_saml_nocert.egg-info/dependency_links.txt
src/python_saml_nocert.egg-info/requires.txt
src/python_saml_nocert.egg-info/top_level.txt