Metadata-Version: 1.1
Name: python-saml-nocert
Version: 2.2.1
Summary: Onelogin Python Toolkit. Add SAML support to your Python software using this library
Home-page: https://github.com/onelogin/python-saml
Author: OneLogin
Author-email: support@onelogin.com
License: MIT
Keywords: saml saml2 xmlsec django flask
Platform: UNKNOWN
Classifier: Development Status :: 5 - Production/Stable
Classifier: Intended Audience :: Developers
Classifier: Intended Audience :: System Administrators
Classifier: Operating System :: OS Independent
Classifier: Programming Language :: Python :: 2.7
